cdktf_cdktf_provider_google_beta/__init__.py
cdktf_cdktf_provider_google_beta/py.typed
cdktf_cdktf_provider_google_beta/_jsii/__init__.py
cdktf_cdktf_provider_google_beta/_jsii/provider-google-beta@14.24.0.jsii.tgz
cdktf_cdktf_provider_google_beta/data_google_access_approval_folder_service_account/__init__.py
cdktf_cdktf_provider_google_beta/data_google_access_approval_organization_service_account/__init__.py
cdktf_cdktf_provider_google_beta/data_google_access_approval_project_service_account/__init__.py
cdktf_cdktf_provider_google_beta/data_google_access_context_manager_access_policy/__init__.py
cdktf_cdktf_provider_google_beta/data_google_access_context_manager_access_policy_iam_policy/__init__.py
cdktf_cdktf_provider_google_beta/data_google_active_folder/__init__.py
cdktf_cdktf_provider_google_beta/data_google_alloydb_cluster/__init__.py
cdktf_cdktf_provider_google_beta/data_google_alloydb_instance/__init__.py
cdktf_cdktf_provider_google_beta/data_google_alloydb_locations/__init__.py
cdktf_cdktf_provider_google_beta/data_google_alloydb_supported_database_flags/__init__.py
cdktf_cdktf_provider_google_beta/data_google_api_gateway_api_config_iam_policy/__init__.py
cdktf_cdktf_provider_google_beta/data_google_api_gateway_api_iam_policy/__init__.py
cdktf_cdktf_provider_google_beta/data_google_api_gateway_gateway_iam_policy/__init__.py
cdktf_cdktf_provider_google_beta/data_google_apigee_environment_iam_policy/__init__.py
cdktf_cdktf_provider_google_beta/data_google_app_engine_default_service_account/__init__.py
cdktf_cdktf_provider_google_beta/data_google_apphub_application/__init__.py
cdktf_cdktf_provider_google_beta/data_google_apphub_discovered_service/__init__.py
cdktf_cdktf_provider_google_beta/data_google_apphub_discovered_workload/__init__.py
cdktf_cdktf_provider_google_beta/data_google_artifact_registry_docker_image/__init__.py
cdktf_cdktf_provider_google_beta/data_google_artifact_registry_locations/__init__.py
cdktf_cdktf_provider_google_beta-14.24.0.dist-info/LICENSE
cdktf_cdktf_provider_google_beta-14.24.0.dist-info/METADATA
cdktf_cdktf_provider_google_beta-14.24.0.dist-info/WHEEL
cdktf_cdktf_provider_google_beta-14.24.0.dist-info/top_level.txt
cdktf_cdktf_provider_google_beta-14.24.0.dist-info/RECORD
